ssb/__init__.py
ssb/local/__init__.py
ssb/local/config.py
ssb/rpc/__init__.py
ssb/rpc/muxrpc.py
ssb/rpc/packet_stream.py
ssb/rpc/feed/__init__.py
ssb/rpc/feed/models.py
ssb/rpc/tests/__init__.py
ssb/rpc/tests/test_feed.py
ssb/rpc/tests/test_packet_stream.py
ssb/rpc/tests/test_util.py
ssb/shs/__init__.py
ssb/shs/boxstream.py
ssb/shs/crypto.py
ssb/shs/network.py
ssb/shs/test_boxstream.py
ssb/shs/test_crypto.py
ssb/shs/test_network.py
ssb/shs/util.py
surfcity/__init__.py
surfcity/__main__.py
surfcity/edlin.py
surfcity/app/__init__.py
surfcity/app/core.py
surfcity/app/db.py
surfcity/app/net.py
surfcity/ui/__init__.py
surfcity/ui/kivy.py
surfcity/ui/tty.py
surfcity/ui/urwid.py
surfcity-0.1.1.dist-info/AUTHORS
surfcity-0.1.1.dist-info/LICENSE
surfcity-0.1.1.dist-info/METADATA
surfcity-0.1.1.dist-info/WHEEL
surfcity-0.1.1.dist-info/entry_points.txt
surfcity-0.1.1.dist-info/top_level.txt
surfcity-0.1.1.dist-info/zip-safe
surfcity-0.1.1.dist-info/RECORD
